unpackable/__init__.py
unpackable/obj.py
unpackable/types.py
unpackable-0.0.4.dist-info/LICENSE
unpackable-0.0.4.dist-info/METADATA
unpackable-0.0.4.dist-info/WHEEL
unpackable-0.0.4.dist-info/top_level.txt
unpackable-0.0.4.dist-info/zip-safe
unpackable-0.0.4.dist-info/RECORD
