Metadata-Version: 2.1
Name: unpackable
Version: 0.0.4
Summary: 📦 Destructure Python objects
Home-page: UNKNOWN
License: LGPL-3.0
Platform: UNKNOWN
Classifier: Programming Language :: Python :: 3
Classifier: Programming Language :: Python :: 3.8
Classifier: Programming Language :: Python :: 3.9
Classifier: Programming Language :: Python :: 3.10
License-File: LICENSE
Requires-Dist: typing-extensions (>=3.10.0.0) ; python_version < "3.10"
